indelprimermapper/__init__.py
indelprimermapper/blast.py
indelprimermapper/genome.py
indelprimermapper/indel.py
indelprimermapper/integration.py
indelprimermapper/io.py
indelprimermapper/pipeline.py
indelprimermapper/primer_design.py
indelprimermapper/ranking.py
indelprimermapper/visualization.py
indelprimermapper-1.0.0.dist-info/LICENSE
indelprimermapper-1.0.0.dist-info/METADATA
indelprimermapper-1.0.0.dist-info/WHEEL
indelprimermapper-1.0.0.dist-info/entry_points.txt
indelprimermapper-1.0.0.dist-info/top_level.txt
indelprimermapper-1.0.0.dist-info/RECORD
