Metadata-Version: 2.1
Name: indelprimermapper
Version: 1.0.0
Summary: Automated indel-based primer design for QTL fine mapping
Home-page: https://github.com/xiaoguanghuan123/fine_mapping_indelPrimerDesign
Author: Guangchao Sun (guangchaosun@sicau.edu.cn)& Changchuang Liu
Author-email: guangchaosun@sicau.edu.cn
License: MIT
Requires-Python: >=3.8
License-File: LICENSE
Requires-Dist: pandas
Requires-Dist: primer3-py
Requires-Dist: pyfaidx
Requires-Dist: biopython
